ayb/__init__.py
ayb/_config.py
ayb/bot.py
ayb/category.py
ayb/client.py
ayb/errors.py
ayb/stats.py
ayb-0.1.dist-info/LICENSE
ayb-0.1.dist-info/METADATA
ayb-0.1.dist-info/WHEEL
ayb-0.1.dist-info/top_level.txt
ayb-0.1.dist-info/RECORD
